datadashr/__init__.py
datadashr/api/__init__.py
datadashr/api/app.py
datadashr/api/crud.py
datadashr/api/datadashr_app.db
datadashr/api/models.py
datadashr/api/robyn.env
datadashr/api/utilities.py
datadashr/app.py
datadashr/config.py
datadashr/context.py
datadashr/core/__init__.py
datadashr/core/embeddings/__init__.py
datadashr/core/embeddings/base_embeddings.py
datadashr/core/embeddings/check_embeddings.py
datadashr/core/embeddings/fastembed_embeddings.py
datadashr/core/embeddings/huggingface_embeddings.py
datadashr/core/embeddings/ollama_embeddings.py
datadashr/core/embeddings/openai_embeddings.py
datadashr/core/importers/__init__.py
datadashr/core/importers/tabular/__init__.py
datadashr/core/importers/tabular/base_importer.py
datadashr/core/importers/tabular/csv_importer.py
datadashr/core/importers/tabular/elasticsearch_importer.py
datadashr/core/importers/tabular/models/__init__.py
datadashr/core/importers/tabular/models/config.py
datadashr/core/importers/tabular/models/import_data_config.py
datadashr/core/importers/tabular/models/source_config.py
datadashr/core/importers/tabular/models/source_mapping.py
datadashr/core/importers/tabular/pandas_importer.py
datadashr/core/importers/tabular/parquet_importer.py
datadashr/core/importers/tabular/polars_importer.py
datadashr/core/importers/tabular/sql_importer.py
datadashr/core/llms/__init__.py
datadashr/core/llms/base_llm.py
datadashr/core/llms/check_llms.py
datadashr/core/llms/groq_llm.py
datadashr/core/llms/huggingface_llm.py
datadashr/core/llms/ollama_llm.py
datadashr/core/llms/openai_llm.py
datadashr/core/pipeline/__init__.py
datadashr/core/pipeline/base.py
datadashr/core/pipeline/context/__init__.py
datadashr/core/pipeline/context/format_context.py
datadashr/core/pipeline/context/format_context_response.py
datadashr/core/pipeline/context/llm_context_request.py
datadashr/core/pipeline/context/retrieve_context.py
datadashr/core/pipeline/data/__init__.py
datadashr/core/pipeline/data/cache_step.py
datadashr-0.2.5.dist-info/METADATA
datadashr-0.2.5.dist-info/WHEEL
datadashr-0.2.5.dist-info/entry_points.txt
datadashr-0.2.5.dist-info/RECORD
