Metadata-Version: 2.1
Name: datadashr
Version: 0.2.5
Summary: Engage with your data (SQL, CSV, pandas, polars, mongodb, noSQL, etc.) using Ollama, an open-source tool that operates locally. Datadashr transforms data analysis into a conversational experience powered by Ollama LLMs and RAG.
License: MIT
Author: Datadashr
Author-email: dev@datadashr.com
Requires-Python: >=3.10,<3.13
Classifier: License :: OSI Approved :: MIT License
Classifier: Programming Language :: Python :: 3
Classifier: Programming Language :: Python :: 3.10
Classifier: Programming Language :: Python :: 3.11
Classifier: Programming Language :: Python :: 3.12
Requires-Dist: astor (>=0.8.1,<0.9.0)
Requires-Dist: chromadb (>=0.5.3,<0.6.0)
Requires-Dist: cryptography (>=42.0.8,<43.0.0)
Requires-Dist: docx2txt (>=0.8,<0.9)
Requires-Dist: duckdb (>=1.0.0,<2.0.0)
Requires-Dist: duckdb-engine (>=0.13.1,<0.14.0)
Requires-Dist: elasticsearch (>=8.14.0,<9.0.0)
Requires-Dist: faiss-cpu (>=1.8.0.post1,<2.0.0)
Requires-Dist: fastembed (>=0.3.1,<0.4.0)
Requires-Dist: groq (>=0.9.0,<0.10.0)
Requires-Dist: jinja2 (>=3.1.4,<4.0.0)
Requires-Dist: lancedb (>=0.8.2,<0.9.0)
Requires-Dist: langchain (>=0.2.5,<0.3.0)
Requires-Dist: langchain-anthropic (>=0.1.15,<0.2.0)
Requires-Dist: langchain-aws (>=0.1.6,<0.2.0)
Requires-Dist: langchain-chroma (>=0.1.1,<0.2.0)
Requires-Dist: langchain-community (>=0.2.5,<0.3.0)
Requires-Dist: langchain-experimental (>=0.0.61,<0.0.62)
Requires-Dist: langchain-google-genai (>=1.0.6,<2.0.0)
Requires-Dist: langchain-groq (>=0.1.5,<0.2.0)
Requires-Dist: langchain-huggingface (>=0.0.3,<0.0.4)
Requires-Dist: langchain-openai (>=0.1.8,<0.2.0)
Requires-Dist: langchain-qdrant (>=0.1.1,<0.2.0)
Requires-Dist: langchainhub (>=0.1.20,<0.2.0)
Requires-Dist: loguru (>=0.7.2,<0.8.0)
Requires-Dist: matplotlib (>=3.9.0,<4.0.0)
Requires-Dist: mpld3 (>=0.5.10,<0.6.0)
Requires-Dist: nicegui (>=1.4.29,<2.0.0)
Requires-Dist: numba (>=0.60.0,<0.61.0)
Requires-Dist: numpy (>=1.26.4,<2.0.0)
Requires-Dist: ollama (>=0.2.0,<0.3.0)
Requires-Dist: openai (>=1.34.0,<2.0.0)
Requires-Dist: openpyxl (>=3.1.5,<4.0.0)
Requires-Dist: opentelemetry-api (>=1.25.0,<2.0.0)
Requires-Dist: pandas (>=2.2.2,<3.0.0)
Requires-Dist: panel (>=1.4.4,<2.0.0)
Requires-Dist: pinecone (>=4.0.0,<5.0.0)
Requires-Dist: pinecone-client[grpc] (>=5.0.1,<6.0.0)
Requires-Dist: poetry-core (>=1.9.0,<2.0.0)
Requires-Dist: polars (>=0.20.31,<0.21.0)
Requires-Dist: pydantic (>=2.7.4,<3.0.0)
Requires-Dist: pymysql (>=1.1.1,<2.0.0)
Requires-Dist: python-dotenv (>=1.0.1,<2.0.0)
Requires-Dist: pywebview (>=5.1,<6.0)
Requires-Dist: requests (>=2.32.3,<3.0.0)
Requires-Dist: restrictedpython (>=7.1,<8.0)
Requires-Dist: robyn (>=0.58.1,<0.59.0)
Requires-Dist: sentence-transformers (>=3.0.0,<4.0.0)
Requires-Dist: sqlalchemy (>=2.0.30,<3.0.0)
Requires-Dist: sqlparse (>=0.5.0,<0.6.0)
Requires-Dist: streamlit (>=1.35.0,<2.0.0)
Requires-Dist: tantivy (>=0.22.0,<0.23.0)
Requires-Dist: tinydb (>=4.8.0,<5.0.0)
Requires-Dist: trafilatura (>=1.10.0,<2.0.0)
Requires-Dist: unstructured[all-docs] (>=0.14.6,<0.15.0)
